{"title": "Ottie’s", "id": "tg-5137713435085111297", "net.maunium.telegram.pack": {"short_name": "OttiesStickers", "hash": "-687584593"}, "stickers": [{"body": "😡", "url": "mxc://poa.st/cLeNBxwlHNkQbcQNwBIHqFTg", "info": {"w": 256, "h": 200, "size": 138585, "mimetype": "image/png", "thumbnail_url": "mxc://poa.st/cLeNBxwlHNkQbcQNwBIHqFTg", "thumbnail_info": {"w": 256, "h": 200, "size": 138585, "mimetype": "image/png"}}, "msgtype": "m.sticker", "id": "tg-5134462265101123815", "net.maunium.telegram.sticker": {"pack": {"id": "5137713435085111297", "short_name": "OttiesStickers"}, "id": "5134462265101123815", "emoticons": ["😡"]}}, {"body": "👍", "url": "mxc://poa.st/BfNOrOJPzkzeIgauWarbvVvG", "info": {"w": 256, "h": 175, "size": 94821, "mimetype": "image/png", "thumbnail_url": "mxc://poa.st/BfNOrOJPzkzeIgauWarbvVvG", "thumbnail_info": {"w": 256, "h": 175, "size": 94821, "mimetype": "image/png"}}, "msgtype": "m.sticker", "id": "tg-5134340408289001843", "net.maunium.telegram.sticker": {"pack": {"id": "5137713435085111297", "short_name": "OttiesStickers"}, "id": "5134340408289001843", "emoticons": ["👍"]}}, {"body": "😂", "url": "mxc://poa.st/ENADgdaWmnSJBZxJNXovzYQO", "info": {"w": 256, "h": 175, "size": 89143, "mimetype": "image/png", "thumbnail_url": "mxc://poa.st/ENADgdaWmnSJBZxJNXovzYQO", "thumbnail_info": {"w": 256, "h": 175, "size": 89143, "mimetype": "image/png"}}, "msgtype": "m.sticker", "id": "tg-5136639749095687097", "net.maunium.telegram.sticker": {"pack": {"id": "5137713435085111297", "short_name": "OttiesStickers"}, "id": "5136639749095687097", "emoticons": ["😂"]}}, {"body": "🤭", "url": "mxc://poa.st/AOOYOIWMRMXRAlqnDMDTPxck", "info": {"w": 256, "h": 175, "size": 98996, "mimetype": "image/png", "thumbnail_url": "mxc://poa.st/AOOYOIWMRMXRAlqnDMDTPxck", "thumbnail_info": {"w": 256, "h": 175, "size": 98996, "mimetype": "image/png"}}, "msgtype": "m.sticker", "id": "tg-5138882615377395994", "net.maunium.telegram.sticker": {"pack": {"id": "5137713435085111297", "short_name": "OttiesStickers"}, "id": "5138882615377395994", "emoticons": ["🤭"]}}, {"body": "☹️", "url": "mxc://poa.st/ISfxItDowhXQVfOwOpOwSXPm", "info": {"w": 256, "h": 175, "size": 85488, "mimetype": "image/png", "thumbnail_url": "mxc://poa.st/ISfxItDowhXQVfOwOpOwSXPm", "thumbnail_info": {"w": 256, "h": 175, "size": 85488, "mimetype": "image/png"}}, "msgtype": "m.sticker", "id": "tg-5136582467116859679", "net.maunium.telegram.sticker": {"pack": {"id": "5137713435085111297", "short_name": "OttiesStickers"}, "id": "5136582467116859679", "emoticons": ["☹"]}}, {"body": "🤬", "url": "mxc://poa.st/xaBrAJXZQmExcNaPMvRgfbZA", "info": {"w": 256, "h": 175, "size": 134210, "mimetype": "image/png", "thumbnail_url": "mxc://poa.st/xaBrAJXZQmExcNaPMvRgfbZA", "thumbnail_info": {"w": 256, "h": 175, "size": 134210, "mimetype": "image/png"}}, "msgtype": "m.sticker", "id": "tg-5134593291668422898", "net.maunium.telegram.sticker": {"pack": {"id": "5137713435085111297", "short_name": "OttiesStickers"}, "id": "5134593291668422898", "emoticons": ["🤬"]}}, {"body": "🍆", "url": "mxc://poa.st/hJRxlKLBRksjNdahzJHzxlEV", "info": {"w": 256, "h": 175, "size": 81354, "mimetype": "image/png", "thumbnail_url": "mxc://poa.st/hJRxlKLBRksjNdahzJHzxlEV", "thumbnail_info": {"w": 256, "h": 175, "size": 81354, "mimetype": "image/png"}}, "msgtype": "m.sticker", "id": "tg-5134293932447891693", "net.maunium.telegram.sticker": {"pack": {"id": "5137713435085111297", "short_name": "OttiesStickers"}, "id": "5134293932447891693", "emoticons": ["🍆"]}}, {"body": "🍗", "url": "mxc://poa.st/LwGbGNOsHQbKJlKfpjoXrqTJ", "info": {"w": 256, "h": 175, "size": 113167, "mimetype": "image/png", "thumbnail_url": "mxc://poa.st/LwGbGNOsHQbKJlKfpjoXrqTJ", "thumbnail_info": {"w": 256, "h": 175, "size": 113167, "mimetype": "image/png"}}, "msgtype": "m.sticker", "id": "tg-5140992178759139666", "net.maunium.telegram.sticker": {"pack": {"id": "5137713435085111297", "short_name": "OttiesStickers"}, "id": "5140992178759139666", "emoticons": ["🍗"]}}, {"body": "😋", "url": "mxc://poa.st/hYNiMOLliiOulCDJLFMqxWNm", "info": {"w": 256, "h": 175, "size": 109931, "mimetype": "image/png", "thumbnail_url": "mxc://poa.st/hYNiMOLliiOulCDJLFMqxWNm", "thumbnail_info": {"w": 256, "h": 175, "size": 109931, "mimetype": "image/png"}}, "msgtype": "m.sticker", "id": "tg-5138694401320550764", "net.maunium.telegram.sticker": {"pack": {"id": "5137713435085111297", "short_name": "OttiesStickers"}, "id": "5138694401320550764", "emoticons": ["😋"]}}, {"body": "😢", "url": "mxc://poa.st/zzirmISJMaZZdelcJQvffsfB", "info": {"w": 256, "h": 200, "size": 138635, "mimetype": "image/png", "thumbnail_url": "mxc://poa.st/zzirmISJMaZZdelcJQvffsfB", "thumbnail_info": {"w": 256, "h": 200, "size": 138635, "mimetype": "image/png"}}, "msgtype": "m.sticker", "id": "tg-5134411447048077832", "net.maunium.telegram.sticker": {"pack": {"id": "5137713435085111297", "short_name": "OttiesStickers"}, "id": "5134411447048077832", "emoticons": ["😢"]}}, {"body": "🫂", "url": "mxc://poa.st/xrxLUEeKCZQmJBSWdVcgsosE", "info": {"w": 256, "h": 175, "size": 107775, "mimetype": "image/png", "thumbnail_url": "mxc://poa.st/xrxLUEeKCZQmJBSWdVcgsosE", "thumbnail_info": {"w": 256, "h": 175, "size": 107775, "mimetype": "image/png"}}, "msgtype": "m.sticker", "id": "tg-5134205962927735006", "net.maunium.telegram.sticker": {"pack": {"id": "5137713435085111297", "short_name": "OttiesStickers"}, "id": "5134205962927735006", "emoticons": ["🫂"]}}, {"body": "😨", "url": "mxc://poa.st/EHnpXHIuDvcScNpEIbBPnyus", "info": {"w": 256, "h": 175, "size": 109915, "mimetype": "image/png", "thumbnail_url": "mxc://poa.st/EHnpXHIuDvcScNpEIbBPnyus", "thumbnail_info": {"w": 256, "h": 175, "size": 109915, "mimetype": "image/png"}}, "msgtype": "m.sticker", "id": "tg-5136909198163968260", "net.maunium.telegram.sticker": {"pack": {"id": "5137713435085111297", "short_name": "OttiesStickers"}, "id": "5136909198163968260", "emoticons": ["😨"]}}, {"body": "🥲", "url": "mxc://poa.st/CmNXYFBbgVjzVTyYKhXJriwd", "info": {"w": 256, "h": 175, "size": 123636, "mimetype": "image/png", "thumbnail_url": "mxc://poa.st/CmNXYFBbgVjzVTyYKhXJriwd", "thumbnail_info": {"w": 256, "h": 175, "size": 123636, "mimetype": "image/png"}}, "msgtype": "m.sticker", "id": "tg-5139005344067879258", "net.maunium.telegram.sticker": {"pack": {"id": "5137713435085111297", "short_name": "OttiesStickers"}, "id": "5139005344067879258", "emoticons": ["🥲"]}}, {"body": "😓", "url": "mxc://poa.st/gJUSlWgwKjUfHIUDHzFpLXQn", "info": {"w": 256, "h": 175, "size": 92811, "mimetype": "image/png", "thumbnail_url": "mxc://poa.st/gJUSlWgwKjUfHIUDHzFpLXQn", "thumbnail_info": {"w": 256, "h": 175, "size": 92811, "mimetype": "image/png"}}, "msgtype": "m.sticker", "id": "tg-5138647349953822944", "net.maunium.telegram.sticker": {"pack": {"id": "5137713435085111297", "short_name": "OttiesStickers"}, "id": "5138647349953822944", "emoticons": ["😓"]}}, {"body": "🤔", "url": "mxc://poa.st/TRvRUPYDCgvHFhPCMaSUuiap", "info": {"w": 256, "h": 175, "size": 106328, "mimetype": "image/png", "thumbnail_url": "mxc://poa.st/TRvRUPYDCgvHFhPCMaSUuiap", "thumbnail_info": {"w": 256, "h": 175, "size": 106328, "mimetype": "image/png"}}, "msgtype": "m.sticker", "id": "tg-5138904717279101176", "net.maunium.telegram.sticker": {"pack": {"id": "5137713435085111297", "short_name": "OttiesStickers"}, "id": "5138904717279101176", "emoticons": ["🤔"]}}, {"body": "🎵", "url": "mxc://poa.st/dBsvbEeoSFQWziojfHuhFfLV", "info": {"w": 256, "h": 175, "size": 140187, "mimetype": "image/png", "thumbnail_url": "mxc://poa.st/dBsvbEeoSFQWziojfHuhFfLV", "thumbnail_info": {"w": 256, "h": 175, "size": 140187, "mimetype": "image/png"}}, "msgtype": "m.sticker", "id": "tg-5143569829151637922", "net.maunium.telegram.sticker": {"pack": {"id": "5137713435085111297", "short_name": "OttiesStickers"}, "id": "5143569829151637922", "emoticons": ["🎵"]}}, {"body": "👀", "url": "mxc://poa.st/BSDKYGMCZFiEAuLPOptazelk", "info": {"w": 256, "h": 175, "size": 61103, "mimetype": "image/png", "thumbnail_url": "mxc://poa.st/BSDKYGMCZFiEAuLPOptazelk", "thumbnail_info": {"w": 256, "h": 175, "size": 61103, "mimetype": "image/png"}}, "msgtype": "m.sticker", "id": "tg-5134351411995214065", "net.maunium.telegram.sticker": {"pack": {"id": "5137713435085111297", "short_name": "OttiesStickers"}, "id": "5134351411995214065", "emoticons": ["👀"]}}, {"body": "🍑", "url": "mxc://poa.st/LrgERMfPiXNNQWCLJbZGrgZy", "info": {"w": 256, "h": 140, "size": 102301, "mimetype": "image/png", "thumbnail_url": "mxc://poa.st/LrgERMfPiXNNQWCLJbZGrgZy", "thumbnail_info": {"w": 256, "h": 140, "size": 102301, "mimetype": "image/png"}}, "msgtype": "m.sticker", "id": "tg-5134382017932165333", "net.maunium.telegram.sticker": {"pack": {"id": "5137713435085111297", "short_name": "OttiesStickers"}, "id": "5134382017932165333", "emoticons": ["🍑"]}}, {"body": "🦦", "url": "mxc://poa.st/MLkcvieaJPmIrEgaQAapJMcY", "info": {"w": 256, "h": 200, "size": 149933, "mimetype": "image/png", "thumbnail_url": "mxc://poa.st/MLkcvieaJPmIrEgaQAapJMcY", "thumbnail_info": {"w": 256, "h": 200, "size": 149933, "mimetype": "image/png"}}, "msgtype": "m.sticker", "id": "tg-5136563466181542131", "net.maunium.telegram.sticker": {"pack": {"id": "5137713435085111297", "short_name": "OttiesStickers"}, "id": "5136563466181542131", "emoticons": ["🦦"]}}, {"body": "🎤", "url": "mxc://poa.st/HXfhbsMzuSfixKSjBFKBmpwi", "info": {"w": 256, "h": 200, "size": 115732, "mimetype": "image/png", "thumbnail_url": "mxc://poa.st/HXfhbsMzuSfixKSjBFKBmpwi", "thumbnail_info": {"w": 256, "h": 200, "size": 115732, "mimetype": "image/png"}}, "msgtype": "m.sticker", "id": "tg-5134342388268925202", "net.maunium.telegram.sticker": {"pack": {"id": "5137713435085111297", "short_name": "OttiesStickers"}, "id": "5134342388268925202", "emoticons": ["🎤"]}}, {"body": "🤡", "url": "mxc://poa.st/qXHYbvocGqnmbTHVjrnHbsKk", "info": {"w": 256, "h": 175, "size": 85347, "mimetype": "image/png", "thumbnail_url": "mxc://poa.st/qXHYbvocGqnmbTHVjrnHbsKk", "thumbnail_info": {"w": 256, "h": 175, "size": 85347, "mimetype": "image/png"}}, "msgtype": "m.sticker", "id": "tg-5134623536828121304", "net.maunium.telegram.sticker": {"pack": {"id": "5137713435085111297", "short_name": "OttiesStickers"}, "id": "5134623536828121304", "emoticons": ["🤡"]}}, {"body": "🥊", "url": "mxc://poa.st/ydgGARsIdzrPCqsKShkuaQIn", "info": {"w": 256, "h": 175, "size": 277804, "mimetype": "image/png", "thumbnail_url": "mxc://poa.st/ydgGARsIdzrPCqsKShkuaQIn", "thumbnail_info": {"w": 256, "h": 175, "size": 277804, "mimetype": "image/png"}}, "msgtype": "m.sticker", "id": "tg-5134114338390409521", "net.maunium.telegram.sticker": {"pack": {"id": "5137713435085111297", "short_name": "OttiesStickers"}, "id": "5134114338390409521", "emoticons": ["🥊"]}}, {"body": "🎣", "url": "mxc://poa.st/FJSAsULlrjLMshbZxIELCrND", "info": {"w": 256, "h": 175, "size": 75504, "mimetype": "image/png", "thumbnail_url": "mxc://poa.st/FJSAsULlrjLMshbZxIELCrND", "thumbnail_info": {"w": 256, "h": 175, "size": 75504, "mimetype": "image/png"}}, "msgtype": "m.sticker", "id": "tg-5136898671199125779", "net.maunium.telegram.sticker": {"pack": {"id": "5137713435085111297", "short_name": "OttiesStickers"}, "id": "5136898671199125779", "emoticons": ["🎣"]}}, {"body": "🥪", "url": "mxc://poa.st/UwUbVtHMpdaZHQiLcEsdEBXR", "info": {"w": 256, "h": 175, "size": 172500, "mimetype": "image/png", "thumbnail_url": "mxc://poa.st/UwUbVtHMpdaZHQiLcEsdEBXR", "thumbnail_info": {"w": 256, "h": 175, "size": 172500, "mimetype": "image/png"}}, "msgtype": "m.sticker", "id": "tg-5134650152740454684", "net.maunium.telegram.sticker": {"pack": {"id": "5137713435085111297", "short_name": "OttiesStickers"}, "id": "5134650152740454684", "emoticons": ["🥪"]}}, {"body": "⛓", "url": "mxc://poa.st/VmYgsIabVVHezenAvdVPvoTj", "info": {"w": 256, "h": 175, "size": 103852, "mimetype": "image/png", "thumbnail_url": "mxc://poa.st/VmYgsIabVVHezenAvdVPvoTj", "thumbnail_info": {"w": 256, "h": 175, "size": 103852, "mimetype": "image/png"}}, "msgtype": "m.sticker", "id": "tg-5134568651441045791", "net.maunium.telegram.sticker": {"pack": {"id": "5137713435085111297", "short_name": "OttiesStickers"}, "id": "5134568651441045791", "emoticons": ["⛓"]}}, {"body": "🖍", "url": "mxc://poa.st/PrsKzkMpYoRxGkUCptFsEZut", "info": {"w": 256, "h": 175, "size": 187377, "mimetype": "image/png", "thumbnail_url": "mxc://poa.st/PrsKzkMpYoRxGkUCptFsEZut", "thumbnail_info": {"w": 256, "h": 175, "size": 187377, "mimetype": "image/png"}}, "msgtype": "m.sticker", "id": "tg-5134312456641839427", "net.maunium.telegram.sticker": {"pack": {"id": "5137713435085111297", "short_name": "OttiesStickers"}, "id": "5134312456641839427", "emoticons": ["🖍"]}}, {"body": "👨‍✈️", "url": "mxc://poa.st/xuLqQlgkYmwUIhdKIqqUTglV", "info": {"w": 256, "h": 175, "size": 137769, "mimetype": "image/png", "thumbnail_url": "mxc://poa.st/xuLqQlgkYmwUIhdKIqqUTglV", "thumbnail_info": {"w": 256, "h": 175, "size": 137769, "mimetype": "image/png"}}, "msgtype": "m.sticker", "id": "tg-5134336783336603998", "net.maunium.telegram.sticker": {"pack": {"id": "5137713435085111297", "short_name": "OttiesStickers"}, "id": "5134336783336603998", "emoticons": ["👨‍✈"]}}, {"body": "😰", "url": "mxc://poa.st/tzjYjlopwzyZzNPMYrTNNFFV", "info": {"w": 256, "h": 175, "size": 150096, "mimetype": "image/png", "thumbnail_url": "mxc://poa.st/tzjYjlopwzyZzNPMYrTNNFFV", "thumbnail_info": {"w": 256, "h": 175, "size": 150096, "mimetype": "image/png"}}, "msgtype": "m.sticker", "id": "tg-5134537517223117168", "net.maunium.telegram.sticker": {"pack": {"id": "5137713435085111297", "short_name": "OttiesStickers"}, "id": "5134537517223117168", "emoticons": ["😰"]}}, {"body": "🍌", "url": "mxc://poa.st/BQiYWEHToPrDshQfjIkMQHZI", "info": {"w": 256, "h": 175, "size": 104450, "mimetype": "image/png", "thumbnail_url": "mxc://poa.st/BQiYWEHToPrDshQfjIkMQHZI", "thumbnail_info": {"w": 256, "h": 175, "size": 104450, "mimetype": "image/png"}}, "msgtype": "m.sticker", "id": "tg-5136609186108408110", "net.maunium.telegram.sticker": {"pack": {"id": "5137713435085111297", "short_name": "OttiesStickers"}, "id": "5136609186108408110", "emoticons": ["🍌"]}}, {"body": "😎", "url": "mxc://poa.st/LwsUpLnfRWJNYxLNBvWEDcia", "info": {"w": 256, "h": 175, "size": 118601, "mimetype": "image/png", "thumbnail_url": "mxc://poa.st/LwsUpLnfRWJNYxLNBvWEDcia", "thumbnail_info": {"w": 256, "h": 175, "size": 118601, "mimetype": "image/png"}}, "msgtype": "m.sticker", "id": "tg-5134277993824256306", "net.maunium.telegram.sticker": {"pack": {"id": "5137713435085111297", "short_name": "OttiesStickers"}, "id": "5134277993824256306", "emoticons": ["😎"]}}, {"body": "😥", "url": "mxc://poa.st/sTMYtXJkaSNLDXfszwxYhqoo", "info": {"w": 256, "h": 175, "size": 130972, "mimetype": "image/png", "thumbnail_url": "mxc://poa.st/sTMYtXJkaSNLDXfszwxYhqoo", "thumbnail_info": {"w": 256, "h": 175, "size": 130972, "mimetype": "image/png"}}, "msgtype": "m.sticker", "id": "tg-5134260689401020734", "net.maunium.telegram.sticker": {"pack": {"id": "5137713435085111297", "short_name": "OttiesStickers"}, "id": "5134260689401020734", "emoticons": ["😥"]}}, {"body": "🐴", "url": "mxc://poa.st/JvSNsSpCkugWpFYteZAaZreb", "info": {"w": 256, "h": 175, "size": 104642, "mimetype": "image/png", "thumbnail_url": "mxc://poa.st/JvSNsSpCkugWpFYteZAaZreb", "thumbnail_info": {"w": 256, "h": 175, "size": 104642, "mimetype": "image/png"}}, "msgtype": "m.sticker", "id": "tg-5134413981078782188", "net.maunium.telegram.sticker": {"pack": {"id": "5137713435085111297", "short_name": "OttiesStickers"}, "id": "5134413981078782188", "emoticons": ["🐴"]}}, {"body": "🎹", "url": "mxc://poa.st/XiGzTbdyUyHZcHzcuAhCeNhj", "info": {"w": 256, "h": 175, "size": 130358, "mimetype": "image/png", "thumbnail_url": "mxc://poa.st/XiGzTbdyUyHZcHzcuAhCeNhj", "thumbnail_info": {"w": 256, "h": 175, "size": 130358, "mimetype": "image/png"}}, "msgtype": "m.sticker", "id": "tg-5134420213076328696", "net.maunium.telegram.sticker": {"pack": {"id": "5137713435085111297", "short_name": "OttiesStickers"}, "id": "5134420213076328696", "emoticons": ["🎹"]}}, {"body": "😭", "url": "mxc://poa.st/xwgacPoNQiYErMVkDiannqdw", "info": {"w": 256, "h": 175, "size": 112155, "mimetype": "image/png", "thumbnail_url": "mxc://poa.st/xwgacPoNQiYErMVkDiannqdw", "thumbnail_info": {"w": 256, "h": 175, "size": 112155, "mimetype": "image/png"}}, "msgtype": "m.sticker", "id": "tg-5134561908342391036", "net.maunium.telegram.sticker": {"pack": {"id": "5137713435085111297", "short_name": "OttiesStickers"}, "id": "5134561908342391036", "emoticons": ["😭"]}}, {"body": "🔨", "url": "mxc://poa.st/lxSfeSOxxgBOmojykuSIATLh", "info": {"w": 256, "h": 175, "size": 89862, "mimetype": "image/png", "thumbnail_url": "mxc://poa.st/lxSfeSOxxgBOmojykuSIATLh", "thumbnail_info": {"w": 256, "h": 175, "size": 89862, "mimetype": "image/png"}}, "msgtype": "m.sticker", "id": "tg-5134294915995402437", "net.maunium.telegram.sticker": {"pack": {"id": "5137713435085111297", "short_name": "OttiesStickers"}, "id": "5134294915995402437", "emoticons": ["🔨"]}}, {"body": "🥳", "url": "mxc://poa.st/NffIOIAyRHdZFtBpQIfFnoBy", "info": {"w": 256, "h": 175, "size": 129140, "mimetype": "image/png", "thumbnail_url": "mxc://poa.st/NffIOIAyRHdZFtBpQIfFnoBy", "thumbnail_info": {"w": 256, "h": 175, "size": 129140, "mimetype": "image/png"}}, "msgtype": "m.sticker", "id": "tg-5134430155925618911", "net.maunium.telegram.sticker": {"pack": {"id": "5137713435085111297", "short_name": "OttiesStickers"}, "id": "5134430155925618911", "emoticons": ["🥳"]}}, {"body": "💪", "url": "mxc://poa.st/dIDUMNIZFjJNzJJzgbcjGGvG", "info": {"w": 256, "h": 175, "size": 107483, "mimetype": "image/png", "thumbnail_url": "mxc://poa.st/dIDUMNIZFjJNzJJzgbcjGGvG", "thumbnail_info": {"w": 256, "h": 175, "size": 107483, "mimetype": "image/png"}}, "msgtype": "m.sticker", "id": "tg-5136462147903029432", "net.maunium.telegram.sticker": {"pack": {"id": "5137713435085111297", "short_name": "OttiesStickers"}, "id": "5136462147903029432", "emoticons": ["💪"]}}, {"body": "🤤", "url": "mxc://poa.st/lSnLdbBPdbQdMPuJLqYoHvbs", "info": {"w": 256, "h": 175, "size": 209096, "mimetype": "image/png", "thumbnail_url": "mxc://poa.st/lSnLdbBPdbQdMPuJLqYoHvbs", "thumbnail_info": {"w": 256, "h": 175, "size": 209096, "mimetype": "image/png"}}, "msgtype": "m.sticker", "id": "tg-5134157167804285212", "net.maunium.telegram.sticker": {"pack": {"id": "5137713435085111297", "short_name": "OttiesStickers"}, "id": "5134157167804285212", "emoticons": ["🤤"]}}, {"body": "😳", "url": "mxc://poa.st/gQzOyOUPBrQuuQEeayMEMNRt", "info": {"w": 256, "h": 175, "size": 180607, "mimetype": "image/png", "thumbnail_url": "mxc://poa.st/gQzOyOUPBrQuuQEeayMEMNRt", "thumbnail_info": {"w": 256, "h": 175, "size": 180607, "mimetype": "image/png"}}, "msgtype": "m.sticker", "id": "tg-5139109625873826704", "net.maunium.telegram.sticker": {"pack": {"id": "5137713435085111297", "short_name": "OttiesStickers"}, "id": "5139109625873826704", "emoticons": ["😳"]}}, {"body": "📖", "url": "mxc://poa.st/YEpONrHtlCPwcLLjkSqHOOHz", "info": {"w": 256, "h": 175, "size": 188753, "mimetype": "image/png", "thumbnail_url": "mxc://poa.st/YEpONrHtlCPwcLLjkSqHOOHz", "thumbnail_info": {"w": 256, "h": 175, "size": 188753, "mimetype": "image/png"}}, "msgtype": "m.sticker", "id": "tg-5143154016187842878", "net.maunium.telegram.sticker": {"pack": {"id": "5137713435085111297", "short_name": "OttiesStickers"}, "id": "5143154016187842878", "emoticons": ["📖"]}}, {"body": "🏒", "url": "mxc://poa.st/PInsJDfDQFPTaCKTSAQPIIRZ", "info": {"w": 256, "h": 200, "size": 160792, "mimetype": "image/png", "thumbnail_url": "mxc://poa.st/PInsJDfDQFPTaCKTSAQPIIRZ", "thumbnail_info": {"w": 256, "h": 200, "size": 160792, "mimetype": "image/png"}}, "msgtype": "m.sticker", "id": "tg-5136357346406039773", "net.maunium.telegram.sticker": {"pack": {"id": "5137713435085111297", "short_name": "OttiesStickers"}, "id": "5136357346406039773", "emoticons": ["🏒"]}}, {"body": "👨‍✈️", "url": "mxc://poa.st/ocOoASqmJLBmpkkFAgsosDXQ", "info": {"w": 256, "h": 175, "size": 89035, "mimetype": "image/png", "thumbnail_url": "mxc://poa.st/ocOoASqmJLBmpkkFAgsosDXQ", "thumbnail_info": {"w": 256, "h": 175, "size": 89035, "mimetype": "image/png"}}, "msgtype": "m.sticker", "id": "tg-5143466423519019366", "net.maunium.telegram.sticker": {"pack": {"id": "5137713435085111297", "short_name": "OttiesStickers"}, "id": "5143466423519019366", "emoticons": ["👨‍✈"]}}, {"body": "🥱", "url": "mxc://poa.st/IaRLYFPkNqtwUHRTOlhprPFg", "info": {"w": 256, "h": 175, "size": 286106, "mimetype": "image/png", "thumbnail_url": "mxc://poa.st/IaRLYFPkNqtwUHRTOlhprPFg", "thumbnail_info": {"w": 256, "h": 175, "size": 286106, "mimetype": "image/png"}}, "msgtype": "m.sticker", "id": "tg-5136804993667432692", "net.maunium.telegram.sticker": {"pack": {"id": "5137713435085111297", "short_name": "OttiesStickers"}, "id": "5136804993667432692", "emoticons": ["🥱"]}}, {"body": "😪", "url": "mxc://poa.st/gHdSlSqDewykIwNeQkvfrRyT", "info": {"w": 256, "h": 144, "size": 172171, "mimetype": "image/png", "thumbnail_url": "mxc://poa.st/gHdSlSqDewykIwNeQkvfrRyT", "thumbnail_info": {"w": 256, "h": 144, "size": 172171, "mimetype": "image/png"}}, "msgtype": "m.sticker", "id": "tg-5150356315565981934", "net.maunium.telegram.sticker": {"pack": {"id": "5137713435085111297", "short_name": "OttiesStickers"}, "id": "5150356315565981934", "emoticons": ["😪"]}}, {"body": "🍆", "url": "mxc://poa.st/ANClbsHOduENdDtYONiaVFaG", "info": {"w": 256, "h": 175, "size": 86048, "mimetype": "image/png", "thumbnail_url": "mxc://poa.st/ANClbsHOduENdDtYONiaVFaG", "thumbnail_info": {"w": 256, "h": 175, "size": 86048, "mimetype": "image/png"}}, "msgtype": "m.sticker", "id": "tg-5150170944777486564", "net.maunium.telegram.sticker": {"pack": {"id": "5137713435085111297", "short_name": "OttiesStickers"}, "id": "5150170944777486564", "emoticons": ["🍆"]}}, {"body": "🥳", "url": "mxc://poa.st/wFgVfLAmMQuUIKhmLBhkSnFd", "info": {"w": 256, "h": 225, "size": 175531, "mimetype": "image/png", "thumbnail_url": "mxc://poa.st/wFgVfLAmMQuUIKhmLBhkSnFd", "thumbnail_info": {"w": 256, "h": 225, "size": 175531, "mimetype": "image/png"}}, "msgtype": "m.sticker", "id": "tg-5154718554934739226", "net.maunium.telegram.sticker": {"pack": {"id": "5137713435085111297", "short_name": "OttiesStickers"}, "id": "5154718554934739226", "emoticons": ["🥳"]}}, {"body": "😰", "url": "mxc://poa.st/YKnXUqoXMCOikBrTExeggJLg", "info": {"w": 256, "h": 175, "size": 108601, "mimetype": "image/png", "thumbnail_url": "mxc://poa.st/YKnXUqoXMCOikBrTExeggJLg", "thumbnail_info": {"w": 256, "h": 175, "size": 108601, "mimetype": "image/png"}}, "msgtype": "m.sticker", "id": "tg-5152453518031847820", "net.maunium.telegram.sticker": {"pack": {"id": "5137713435085111297", "short_name": "OttiesStickers"}, "id": "5152453518031847820", "emoticons": ["😰"]}}, {"body": "👃", "url": "mxc://poa.st/tbcKIUqjNUQgnKZdmmGwLgHT", "info": {"w": 256, "h": 175, "size": 91310, "mimetype": "image/png", "thumbnail_url": "mxc://poa.st/tbcKIUqjNUQgnKZdmmGwLgHT", "thumbnail_info": {"w": 256, "h": 175, "size": 91310, "mimetype": "image/png"}}, "msgtype": "m.sticker", "id": "tg-5166089218857894215", "net.maunium.telegram.sticker": {"pack": {"id": "5137713435085111297", "short_name": "OttiesStickers"}, "id": "5166089218857894215", "emoticons": ["👃"]}}, {"body": "🔫", "url": "mxc://poa.st/IsXsMAbaEEzuMDbQWvZsRQeP", "info": {"w": 256, "h": 144, "size": 86000, "mimetype": "image/png", "thumbnail_url": "mxc://poa.st/IsXsMAbaEEzuMDbQWvZsRQeP", "thumbnail_info": {"w": 256, "h": 144, "size": 86000, "mimetype": "image/png"}}, "msgtype": "m.sticker", "id": "tg-5163640675182313872", "net.maunium.telegram.sticker": {"pack": {"id": "5137713435085111297", "short_name": "OttiesStickers"}, "id": "5163640675182313872", "emoticons": ["🔫"]}}, {"body": "👟", "url": "mxc://poa.st/iQpsLiIOWDlnadXqsjHCSERb", "info": {"w": 256, "h": 175, "size": 84835, "mimetype": "image/png", "thumbnail_url": "mxc://poa.st/iQpsLiIOWDlnadXqsjHCSERb", "thumbnail_info": {"w": 256, "h": 175, "size": 84835, "mimetype": "image/png"}}, "msgtype": "m.sticker", "id": "tg-5163806044308111883", "net.maunium.telegram.sticker": {"pack": {"id": "5137713435085111297", "short_name": "OttiesStickers"}, "id": "5163806044308111883", "emoticons": ["👟"]}}, {"body": "🏝", "url": "mxc://poa.st/awfQfvDChQrnLJsLahkqPySx", "info": {"w": 256, "h": 144, "size": 117317, "mimetype": "image/png", "thumbnail_url": "mxc://poa.st/awfQfvDChQrnLJsLahkqPySx", "thumbnail_info": {"w": 256, "h": 144, "size": 117317, "mimetype": "image/png"}}, "msgtype": "m.sticker", "id": "tg-5165974869648605636", "net.maunium.telegram.sticker": {"pack": {"id": "5137713435085111297", "short_name": "OttiesStickers"}, "id": "5165974869648605636", "emoticons": ["🏝"]}}, {"body": "😠", "url": "mxc://poa.st/aEDaoaAkedGAQGGibTmXedOL", "info": {"w": 256, "h": 144, "size": 100220, "mimetype": "image/png", "thumbnail_url": "mxc://poa.st/aEDaoaAkedGAQGGibTmXedOL", "thumbnail_info": {"w": 256, "h": 144, "size": 100220, "mimetype": "image/png"}}, "msgtype": "m.sticker", "id": "tg-5181552441153290806", "net.maunium.telegram.sticker": {"pack": {"id": "5137713435085111297", "short_name": "OttiesStickers"}, "id": "5181552441153290806", "emoticons": ["😠"]}}, {"body": "🖐", "url": "mxc://poa.st/hHTQyaxgpumOxYSKpfBwdhBF", "info": {"w": 256, "h": 144, "size": 114031, "mimetype": "image/png", "thumbnail_url": "mxc://poa.st/hHTQyaxgpumOxYSKpfBwdhBF", "thumbnail_info": {"w": 256, "h": 144, "size": 114031, "mimetype": "image/png"}}, "msgtype": "m.sticker", "id": "tg-5186322225673798168", "net.maunium.telegram.sticker": {"pack": {"id": "5137713435085111297", "short_name": "OttiesStickers"}, "id": "5186322225673798168", "emoticons": ["🖐"]}}, {"body": "💀", "url": "mxc://poa.st/GMdmOFzHlXovOXQwADQWlyzQ", "info": {"w": 256, "h": 144, "size": 109793, "mimetype": "image/png", "thumbnail_url": "mxc://poa.st/GMdmOFzHlXovOXQwADQWlyzQ", "thumbnail_info": {"w": 256, "h": 144, "size": 109793, "mimetype": "image/png"}}, "msgtype": "m.sticker", "id": "tg-5186313640034173352", "net.maunium.telegram.sticker": {"pack": {"id": "5137713435085111297", "short_name": "OttiesStickers"}, "id": "5186313640034173352", "emoticons": ["💀"]}}, {"body": "😡", "url": "mxc://poa.st/vcDYRRSYjeHPxdHPjIAaZDnw", "info": {"w": 256, "h": 144, "size": 99309, "mimetype": "image/png", "thumbnail_url": "mxc://poa.st/vcDYRRSYjeHPxdHPjIAaZDnw", "thumbnail_info": {"w": 256, "h": 144, "size": 99309, "mimetype": "image/png"}}, "msgtype": "m.sticker", "id": "tg-4900326224653451640", "net.maunium.telegram.sticker": {"pack": {"id": "5137713435085111297", "short_name": "OttiesStickers"}, "id": "4900326224653451640", "emoticons": ["😡"]}}, {"body": "🔫", "url": "mxc://poa.st/wUrNKaZoWjzCSbYKxIVVoAzb", "info": {"w": 256, "h": 150, "size": 81133, "mimetype": "image/png", "thumbnail_url": "mxc://poa.st/wUrNKaZoWjzCSbYKxIVVoAzb", "thumbnail_info": {"w": 256, "h": 150, "size": 81133, "mimetype": "image/png"}}, "msgtype": "m.sticker", "id": "tg-4904869084576874963", "net.maunium.telegram.sticker": {"pack": {"id": "5137713435085111297", "short_name": "OttiesStickers"}, "id": "4904869084576874963", "emoticons": ["🔫"]}}, {"body": "😾", "url": "mxc://poa.st/fDpSJMsyOeAAXyGVJVbazKal", "info": {"w": 256, "h": 150, "size": 79481, "mimetype": "image/png", "thumbnail_url": "mxc://poa.st/fDpSJMsyOeAAXyGVJVbazKal", "thumbnail_info": {"w": 256, "h": 150, "size": 79481, "mimetype": "image/png"}}, "msgtype": "m.sticker", "id": "tg-4904555942806290996", "net.maunium.telegram.sticker": {"pack": {"id": "5137713435085111297", "short_name": "OttiesStickers"}, "id": "4904555942806290996", "emoticons": ["😾"]}}, {"body": "🤗", "url": "mxc://poa.st/whclRlbTDqIpDecfukAulpBm", "info": {"w": 256, "h": 144, "size": 67241, "mimetype": "image/png", "thumbnail_url": "mxc://poa.st/whclRlbTDqIpDecfukAulpBm", "thumbnail_info": {"w": 256, "h": 144, "size": 67241, "mimetype": "image/png"}}, "msgtype": "m.sticker", "id": "tg-4911702609473044697", "net.maunium.telegram.sticker": {"pack": {"id": "5137713435085111297", "short_name": "OttiesStickers"}, "id": "4911702609473044697", "emoticons": ["🤗"]}}, {"body": "🧯", "url": "mxc://poa.st/XWpcoenfSpMcvIvBMGhpyPqw", "info": {"w": 256, "h": 150, "size": 164568, "mimetype": "image/png", "thumbnail_url": "mxc://poa.st/XWpcoenfSpMcvIvBMGhpyPqw", "thumbnail_info": {"w": 256, "h": 150, "size": 164568, "mimetype": "image/png"}}, "msgtype": "m.sticker", "id": "tg-4920674555636220310", "net.maunium.telegram.sticker": {"pack": {"id": "5137713435085111297", "short_name": "OttiesStickers"}, "id": "4920674555636220310", "emoticons": ["🧯"]}}, {"body": "🥛", "url": "mxc://poa.st/bvxSiUnleBWDPdgaCLQkhGKS", "info": {"w": 256, "h": 144, "size": 82285, "mimetype": "image/png", "thumbnail_url": "mxc://poa.st/bvxSiUnleBWDPdgaCLQkhGKS", "thumbnail_info": {"w": 256, "h": 144, "size": 82285, "mimetype": "image/png"}}, "msgtype": "m.sticker", "id": "tg-4924707547107033435", "net.maunium.telegram.sticker": {"pack": {"id": "5137713435085111297", "short_name": "OttiesStickers"}, "id": "4924707547107033435", "emoticons": ["🥛"]}}, {"body": "😏", "url": "mxc://poa.st/nyzZnSWJAumKvCIklUgGnDKa", "info": {"w": 256, "h": 144, "size": 92462, "mimetype": "image/png", "thumbnail_url": "mxc://poa.st/nyzZnSWJAumKvCIklUgGnDKa", "thumbnail_info": {"w": 256, "h": 144, "size": 92462, "mimetype": "image/png"}}, "msgtype": "m.sticker", "id": "tg-4934080604560949428", "net.maunium.telegram.sticker": {"pack": {"id": "5137713435085111297", "short_name": "OttiesStickers"}, "id": "4934080604560949428", "emoticons": ["😏"]}}, {"body": "🤨", "url": "mxc://poa.st/BunazYHzmYuLtTjctwTsMNpD", "info": {"w": 256, "h": 150, "size": 80204, "mimetype": "image/png", "thumbnail_url": "mxc://poa.st/BunazYHzmYuLtTjctwTsMNpD", "thumbnail_info": {"w": 256, "h": 150, "size": 80204, "mimetype": "image/png"}}, "msgtype": "m.sticker", "id": "tg-4936414610048680352", "net.maunium.telegram.sticker": {"pack": {"id": "5137713435085111297", "short_name": "OttiesStickers"}, "id": "4936414610048680352", "emoticons": ["🤨"]}}, {"body": "😁", "url": "mxc://poa.st/rAelMluceniGhnXlvxxDPugi", "info": {"w": 256, "h": 150, "size": 81687, "mimetype": "image/png", "thumbnail_url": "mxc://poa.st/rAelMluceniGhnXlvxxDPugi", "thumbnail_info": {"w": 256, "h": 150, "size": 81687, "mimetype": "image/png"}}, "msgtype": "m.sticker", "id": "tg-4943023254752199525", "net.maunium.telegram.sticker": {"pack": {"id": "5137713435085111297", "short_name": "OttiesStickers"}, "id": "4943023254752199525", "emoticons": ["😁"]}}, {"body": "🩳", "url": "mxc://poa.st/VqfgepFFnxQPPvlaKiaFycKM", "info": {"w": 256, "h": 150, "size": 97600, "mimetype": "image/png", "thumbnail_url": "mxc://poa.st/VqfgepFFnxQPPvlaKiaFycKM", "thumbnail_info": {"w": 256, "h": 150, "size": 97600, "mimetype": "image/png"}}, "msgtype": "m.sticker", "id": "tg-4942849446015664410", "net.maunium.telegram.sticker": {"pack": {"id": "5137713435085111297", "short_name": "OttiesStickers"}, "id": "4942849446015664410", "emoticons": ["🩳"]}}, {"body": "🍆", "url": "mxc://poa.st/MVpGLDmIYvCnEzqmiGLwxkEi", "info": {"w": 256, "h": 150, "size": 98806, "mimetype": "image/png", "thumbnail_url": "mxc://poa.st/MVpGLDmIYvCnEzqmiGLwxkEi", "thumbnail_info": {"w": 256, "h": 150, "size": 98806, "mimetype": "image/png"}}, "msgtype": "m.sticker", "id": "tg-4947496287097323838", "net.maunium.telegram.sticker": {"pack": {"id": "5137713435085111297", "short_name": "OttiesStickers"}, "id": "4947496287097323838", "emoticons": ["🍆"]}}, {"body": "🥛", "url": "mxc://poa.st/UOddiVtNaRtsEqCVaGePPpEG", "info": {"w": 256, "h": 150, "size": 110002, "mimetype": "image/png", "thumbnail_url": "mxc://poa.st/UOddiVtNaRtsEqCVaGePPpEG", "thumbnail_info": {"w": 256, "h": 150, "size": 110002, "mimetype": "image/png"}}, "msgtype": "m.sticker", "id": "tg-4951839469696189245", "net.maunium.telegram.sticker": {"pack": {"id": "5137713435085111297", "short_name": "OttiesStickers"}, "id": "4951839469696189245", "emoticons": ["🥛"]}}, {"body": "💩", "url": "mxc://poa.st/buAAnRGZXMiQgQnfBNoroUkf", "info": {"w": 256, "h": 150, "size": 221137, "mimetype": "image/png", "thumbnail_url": "mxc://poa.st/buAAnRGZXMiQgQnfBNoroUkf", "thumbnail_info": {"w": 256, "h": 150, "size": 221137, "mimetype": "image/png"}}, "msgtype": "m.sticker", "id": "tg-4954057141699740152", "net.maunium.telegram.sticker": {"pack": {"id": "5137713435085111297", "short_name": "OttiesStickers"}, "id": "4954057141699740152", "emoticons": ["💩"]}}, {"body": "👍", "url": "mxc://poa.st/PNoBHwRXVgyVLsfiEvkBCCOH", "info": {"w": 256, "h": 150, "size": 90127, "mimetype": "image/png", "thumbnail_url": "mxc://poa.st/PNoBHwRXVgyVLsfiEvkBCCOH", "thumbnail_info": {"w": 256, "h": 150, "size": 90127, "mimetype": "image/png"}}, "msgtype": "m.sticker", "id": "tg-4958967375945793861", "net.maunium.telegram.sticker": {"pack": {"id": "5137713435085111297", "short_name": "OttiesStickers"}, "id": "4958967375945793861", "emoticons": ["👍"]}}, {"body": "🥃", "url": "mxc://poa.st/mOqzcCupMzrozcmWOPKbgsAr", "info": {"w": 256, "h": 150, "size": 70006, "mimetype": "image/png", "thumbnail_url": "mxc://poa.st/mOqzcCupMzrozcmWOPKbgsAr", "thumbnail_info": {"w": 256, "h": 150, "size": 70006, "mimetype": "image/png"}}, "msgtype": "m.sticker", "id": "tg-4967962536407204187", "net.maunium.telegram.sticker": {"pack": {"id": "5137713435085111297", "short_name": "OttiesStickers"}, "id": "4967962536407204187", "emoticons": ["🥃"]}}, {"body": "😟", "url": "mxc://poa.st/JqBezkcndkEpCHmBtegdgvEd", "info": {"w": 256, "h": 150, "size": 128507, "mimetype": "image/png", "thumbnail_url": "mxc://poa.st/JqBezkcndkEpCHmBtegdgvEd", "thumbnail_info": {"w": 256, "h": 150, "size": 128507, "mimetype": "image/png"}}, "msgtype": "m.sticker", "id": "tg-4970030868102906137", "net.maunium.telegram.sticker": {"pack": {"id": "5137713435085111297", "short_name": "OttiesStickers"}, "id": "4970030868102906137", "emoticons": ["😟"]}}, {"body": "😠", "url": "mxc://poa.st/CyKIoMOLEWWVBSMVMEukubHH", "info": {"w": 256, "h": 150, "size": 79846, "mimetype": "image/png", "thumbnail_url": "mxc://poa.st/CyKIoMOLEWWVBSMVMEukubHH", "thumbnail_info": {"w": 256, "h": 150, "size": 79846, "mimetype": "image/png"}}, "msgtype": "m.sticker", "id": "tg-4972461609139044623", "net.maunium.telegram.sticker": {"pack": {"id": "5137713435085111297", "short_name": "OttiesStickers"}, "id": "4972461609139044623", "emoticons": ["😠"]}}, {"body": "🤨", "url": "mxc://poa.st/lSAJSrehlhMNLsoGpziqBUcj", "info": {"w": 256, "h": 150, "size": 73870, "mimetype": "image/png", "thumbnail_url": "mxc://poa.st/lSAJSrehlhMNLsoGpziqBUcj", "thumbnail_info": {"w": 256, "h": 150, "size": 73870, "mimetype": "image/png"}}, "msgtype": "m.sticker", "id": "tg-4972510524521578966", "net.maunium.telegram.sticker": {"pack": {"id": "5137713435085111297", "short_name": "OttiesStickers"}, "id": "4972510524521578966", "emoticons": ["🤨"]}}, {"body": "😆", "url": "mxc://poa.st/zwZGUyCslzKrWUHgBYfEZOto", "info": {"w": 256, "h": 150, "size": 78206, "mimetype": "image/png", "thumbnail_url": "mxc://poa.st/zwZGUyCslzKrWUHgBYfEZOto", "thumbnail_info": {"w": 256, "h": 150, "size": 78206, "mimetype": "image/png"}}, "msgtype": "m.sticker", "id": "tg-4970158626200093131", "net.maunium.telegram.sticker": {"pack": {"id": "5137713435085111297", "short_name": "OttiesStickers"}, "id": "4970158626200093131", "emoticons": ["😆"]}}, {"body": "😖", "url": "mxc://poa.st/KlZOrLlCvUduexIZwXbrxvbX", "info": {"w": 256, "h": 150, "size": 70966, "mimetype": "image/png", "thumbnail_url": "mxc://poa.st/KlZOrLlCvUduexIZwXbrxvbX", "thumbnail_info": {"w": 256, "h": 150, "size": 70966, "mimetype": "image/png"}}, "msgtype": "m.sticker", "id": "tg-4976597860213588328", "net.maunium.telegram.sticker": {"pack": {"id": "5137713435085111297", "short_name": "OttiesStickers"}, "id": "4976597860213588328", "emoticons": ["😖"]}}, {"body": "🏎", "url": "mxc://poa.st/lMCzRPxAHynbvrdnPMEhVXrJ", "info": {"w": 256, "h": 150, "size": 108243, "mimetype": "image/png", "thumbnail_url": "mxc://poa.st/lMCzRPxAHynbvrdnPMEhVXrJ", "thumbnail_info": {"w": 256, "h": 150, "size": 108243, "mimetype": "image/png"}}, "msgtype": "m.sticker", "id": "tg-4994612499241238730", "net.maunium.telegram.sticker": {"pack": {"id": "5137713435085111297", "short_name": "OttiesStickers"}, "id": "4994612499241238730", "emoticons": ["🏎"]}}, {"body": "❤️", "url": "mxc://poa.st/vHDOYjqRxESgQlfoaTHCvpGd", "info": {"w": 256, "h": 140, "size": 49290, "mimetype": "image/png", "thumbnail_url": "mxc://poa.st/vHDOYjqRxESgQlfoaTHCvpGd", "thumbnail_info": {"w": 256, "h": 140, "size": 49290, "mimetype": "image/png"}}, "msgtype": "m.sticker", "id": "tg-4996985279693717819", "net.maunium.telegram.sticker": {"pack": {"id": "5137713435085111297", "short_name": "OttiesStickers"}, "id": "4996985279693717819", "emoticons": ["❤"]}}, {"body": "😑", "url": "mxc://poa.st/qRkqUCLRxuWdquxWKviFcIwj", "info": {"w": 256, "h": 140, "size": 133506, "mimetype": "image/png", "thumbnail_url": "mxc://poa.st/qRkqUCLRxuWdquxWKviFcIwj", "thumbnail_info": {"w": 256, "h": 140, "size": 133506, "mimetype": "image/png"}}, "msgtype": "m.sticker", "id": "tg-5022073102792655144", "net.maunium.telegram.sticker": {"pack": {"id": "5137713435085111297", "short_name": "OttiesStickers"}, "id": "5022073102792655144", "emoticons": ["😑"]}}, {"body": "😑", "url": "mxc://poa.st/GMMJgeEFdmGnqMoFZKMYqoRP", "info": {"w": 256, "h": 140, "size": 207496, "mimetype": "image/png", "thumbnail_url": "mxc://poa.st/GMMJgeEFdmGnqMoFZKMYqoRP", "thumbnail_info": {"w": 256, "h": 140, "size": 207496, "mimetype": "image/png"}}, "msgtype": "m.sticker", "id": "tg-5021786555459568053", "net.maunium.telegram.sticker": {"pack": {"id": "5137713435085111297", "short_name": "OttiesStickers"}, "id": "5021786555459568053", "emoticons": ["😑"]}}, {"body": "👑", "url": "mxc://poa.st/RWcyyWrVzqQsaikpejypuYjE", "info": {"w": 256, "h": 140, "size": 128393, "mimetype": "image/png", "thumbnail_url": "mxc://poa.st/RWcyyWrVzqQsaikpejypuYjE", "thumbnail_info": {"w": 256, "h": 140, "size": 128393, "mimetype": "image/png"}}, "msgtype": "m.sticker", "id": "tg-5048544270433124862", "net.maunium.telegram.sticker": {"pack": {"id": "5137713435085111297", "short_name": "OttiesStickers"}, "id": "5048544270433124862", "emoticons": ["👑"]}}, {"body": "🔴", "url": "mxc://poa.st/eLSofrdwVXjgGPutonqFlzuS", "info": {"w": 256, "h": 150, "size": 72707, "mimetype": "image/png", "thumbnail_url": "mxc://poa.st/eLSofrdwVXjgGPutonqFlzuS", "thumbnail_info": {"w": 256, "h": 150, "size": 72707, "mimetype": "image/png"}}, "msgtype": "m.sticker", "id": "tg-5068997398617915772", "net.maunium.telegram.sticker": {"pack": {"id": "5137713435085111297", "short_name": "OttiesStickers"}, "id": "5068997398617915772", "emoticons": ["🔴"]}}, {"body": "🟢", "url": "mxc://poa.st/PVgYWJJNJvJvfNiwqvXCCgDl", "info": {"w": 256, "h": 150, "size": 70482, "mimetype": "image/png", "thumbnail_url": "mxc://poa.st/PVgYWJJNJvJvfNiwqvXCCgDl", "thumbnail_info": {"w": 256, "h": 150, "size": 70482, "mimetype": "image/png"}}, "msgtype": "m.sticker", "id": "tg-5069163270254887225", "net.maunium.telegram.sticker": {"pack": {"id": "5137713435085111297", "short_name": "OttiesStickers"}, "id": "5069163270254887225", "emoticons": ["🟢"]}}, {"body": "🥺", "url": "mxc://poa.st/qtZjiabScrZkphQtGCgDxRZC", "info": {"w": 256, "h": 140, "size": 78202, "mimetype": "image/png", "thumbnail_url": "mxc://poa.st/qtZjiabScrZkphQtGCgDxRZC", "thumbnail_info": {"w": 256, "h": 140, "size": 78202, "mimetype": "image/png"}}, "msgtype": "m.sticker", "id": "tg-5177255867539521931", "net.maunium.telegram.sticker": {"pack": {"id": "5137713435085111297", "short_name": "OttiesStickers"}, "id": "5177255867539521931", "emoticons": ["🥺"]}}, {"body": "😡", "url": "mxc://poa.st/ozJnYpJaCvriFHijZjrnriPw", "info": {"w": 256, "h": 140, "size": 83929, "mimetype": "image/png", "thumbnail_url": "mxc://poa.st/ozJnYpJaCvriFHijZjrnriPw", "thumbnail_info": {"w": 256, "h": 140, "size": 83929, "mimetype": "image/png"}}, "msgtype": "m.sticker", "id": "tg-5179668350669685201", "net.maunium.telegram.sticker": {"pack": {"id": "5137713435085111297", "short_name": "OttiesStickers"}, "id": "5179668350669685201", "emoticons": ["😡"]}}, {"body": "😤", "url": "mxc://poa.st/hNZbbkAVquuFDFMPBFxYkLxG", "info": {"w": 256, "h": 140, "size": 77642, "mimetype": "image/png", "thumbnail_url": "mxc://poa.st/hNZbbkAVquuFDFMPBFxYkLxG", "thumbnail_info": {"w": 256, "h": 140, "size": 77642, "mimetype": "image/png"}}, "msgtype": "m.sticker", "id": "tg-5177029372439167478", "net.maunium.telegram.sticker": {"pack": {"id": "5137713435085111297", "short_name": "OttiesStickers"}, "id": "5177029372439167478", "emoticons": ["😤"]}}, {"body": "🤨", "url": "mxc://poa.st/vlcivLnNIKEDvhKllstKgLme", "info": {"w": 256, "h": 256, "size": 127175, "mimetype": "image/png", "thumbnail_url": "mxc://poa.st/vlcivLnNIKEDvhKllstKgLme", "thumbnail_info": {"w": 256, "h": 256, "size": 127175, "mimetype": "image/png"}}, "msgtype": "m.sticker", "id": "tg-4904747816175272660", "net.maunium.telegram.sticker": {"pack": {"id": "5137713435085111297", "short_name": "OttiesStickers"}, "id": "4904747816175272660", "emoticons": ["🤨"]}}, {"body": "📕", "url": "mxc://poa.st/tPtLOzuTAodGrbJsyCIFmXRJ", "info": {"w": 256, "h": 150, "size": 138977, "mimetype": "image/png", "thumbnail_url": "mxc://poa.st/tPtLOzuTAodGrbJsyCIFmXRJ", "thumbnail_info": {"w": 256, "h": 150, "size": 138977, "mimetype": "image/png"}}, "msgtype": "m.sticker", "id": "tg-5041876368065823103", "net.maunium.telegram.sticker": {"pack": {"id": "5137713435085111297", "short_name": "OttiesStickers"}, "id": "5041876368065823103", "emoticons": ["📕"]}}, {"body": "🔨", "url": "mxc://poa.st/IEmoPjKBnAZnNjltqexwSHEZ", "info": {"w": 256, "h": 200, "size": 128019, "mimetype": "image/png", "thumbnail_url": "mxc://poa.st/IEmoPjKBnAZnNjltqexwSHEZ", "thumbnail_info": {"w": 256, "h": 200, "size": 128019, "mimetype": "image/png"}}, "msgtype": "m.sticker", "id": "tg-5053355183560458867", "net.maunium.telegram.sticker": {"pack": {"id": "5137713435085111297", "short_name": "OttiesStickers"}, "id": "5053355183560458867", "emoticons": ["🔨"]}}, {"body": "1️⃣", "url": "mxc://poa.st/QuoDlqPeAGQyPVyrvTZkDasB", "info": {"w": 256, "h": 200, "size": 68222, "mimetype": "image/png", "thumbnail_url": "mxc://poa.st/QuoDlqPeAGQyPVyrvTZkDasB", "thumbnail_info": {"w": 256, "h": 200, "size": 68222, "mimetype": "image/png"}}, "msgtype": "m.sticker", "id": "tg-5084651107007857060", "net.maunium.telegram.sticker": {"pack": {"id": "5137713435085111297", "short_name": "OttiesStickers"}, "id": "5084651107007857060", "emoticons": ["1⃣"]}}, {"body": "2️⃣", "url": "mxc://poa.st/jNDmQyChUqpzsOrMFYUcwvfZ", "info": {"w": 256, "h": 200, "size": 61473, "mimetype": "image/png", "thumbnail_url": "mxc://poa.st/jNDmQyChUqpzsOrMFYUcwvfZ", "thumbnail_info": {"w": 256, "h": 200, "size": 61473, "mimetype": "image/png"}}, "msgtype": "m.sticker", "id": "tg-5085119855443575253", "net.maunium.telegram.sticker": {"pack": {"id": "5137713435085111297", "short_name": "OttiesStickers"}, "id": "5085119855443575253", "emoticons": ["2⃣"]}}, {"body": "3️⃣", "url": "mxc://poa.st/WJjJaugRDNGyqLakZvbKtJbX", "info": {"w": 256, "h": 200, "size": 74353, "mimetype": "image/png", "thumbnail_url": "mxc://poa.st/WJjJaugRDNGyqLakZvbKtJbX", "thumbnail_info": {"w": 256, "h": 200, "size": 74353, "mimetype": "image/png"}}, "msgtype": "m.sticker", "id": "tg-5084730370629304748", "net.maunium.telegram.sticker": {"pack": {"id": "5137713435085111297", "short_name": "OttiesStickers"}, "id": "5084730370629304748", "emoticons": ["3⃣"]}}, {"body": "🎃", "url": "mxc://poa.st/gVlSvhUSQrvUOuaNRIWKiJcP", "info": {"w": 256, "h": 150, "size": 105186, "mimetype": "image/png", "thumbnail_url": "mxc://poa.st/gVlSvhUSQrvUOuaNRIWKiJcP", "thumbnail_info": {"w": 256, "h": 150, "size": 105186, "mimetype": "image/png"}}, "msgtype": "m.sticker", "id": "tg-5102706238987174333", "net.maunium.telegram.sticker": {"pack": {"id": "5137713435085111297", "short_name": "OttiesStickers"}, "id": "5102706238987174333", "emoticons": ["🎃"]}}, {"body": "🧑‍🦰", "url": "mxc://poa.st/RKcVHIzFekbgeMFIAVzCJExR", "info": {"w": 256, "h": 200, "size": 113425, "mimetype": "image/png", "thumbnail_url": "mxc://poa.st/RKcVHIzFekbgeMFIAVzCJExR", "thumbnail_info": {"w": 256, "h": 200, "size": 113425, "mimetype": "image/png"}}, "msgtype": "m.sticker", "id": "tg-5120614014933533127", "net.maunium.telegram.sticker": {"pack": {"id": "5137713435085111297", "short_name": "OttiesStickers"}, "id": "5120614014933533127", "emoticons": ["🧑‍🦰"]}}, {"body": "👨‍⚖️", "url": "mxc://poa.st/rDGjavUCxXWyMVxyqQnSpzxh", "info": {"w": 256, "h": 200, "size": 100064, "mimetype": "image/png", "thumbnail_url": "mxc://poa.st/rDGjavUCxXWyMVxyqQnSpzxh", "thumbnail_info": {"w": 256, "h": 200, "size": 100064, "mimetype": "image/png"}}, "msgtype": "m.sticker", "id": "tg-5127349928107967028", "net.maunium.telegram.sticker": {"pack": {"id": "5137713435085111297", "short_name": "OttiesStickers"}, "id": "5127349928107967028", "emoticons": ["👨‍⚖"]}}, {"body": "😓", "url": "mxc://poa.st/EEncJYpcHWwvgKutHEnwzFMi", "info": {"w": 256, "h": 200, "size": 70321, "mimetype": "image/png", "thumbnail_url": "mxc://poa.st/EEncJYpcHWwvgKutHEnwzFMi", "thumbnail_info": {"w": 256, "h": 200, "size": 70321, "mimetype": "image/png"}}, "msgtype": "m.sticker", "id": "tg-5136494042330169780", "net.maunium.telegram.sticker": {"pack": {"id": "5137713435085111297", "short_name": "OttiesStickers"}, "id": "5136494042330169780", "emoticons": ["😓"]}}, {"body": "🤲", "url": "mxc://poa.st/qlCqTzOtQGqewYnBTezTcSTC", "info": {"w": 256, "h": 200, "size": 110164, "mimetype": "image/png", "thumbnail_url": "mxc://poa.st/qlCqTzOtQGqewYnBTezTcSTC", "thumbnail_info": {"w": 256, "h": 200, "size": 110164, "mimetype": "image/png"}}, "msgtype": "m.sticker", "id": "tg-5138997626011648457", "net.maunium.telegram.sticker": {"pack": {"id": "5137713435085111297", "short_name": "OttiesStickers"}, "id": "5138997626011648457", "emoticons": ["🤲"]}}, {"body": "😮‍💨", "url": "mxc://poa.st/LSaTzstpBjdWQDptNzIBPPYN", "info": {"w": 256, "h": 200, "size": 82003, "mimetype": "image/png", "thumbnail_url": "mxc://poa.st/LSaTzstpBjdWQDptNzIBPPYN", "thumbnail_info": {"w": 256, "h": 200, "size": 82003, "mimetype": "image/png"}}, "msgtype": "m.sticker", "id": "tg-5136846921138176785", "net.maunium.telegram.sticker": {"pack": {"id": "5137713435085111297", "short_name": "OttiesStickers"}, "id": "5136846921138176785", "emoticons": ["😮‍💨"]}}, {"body": "🔦", "url": "mxc://poa.st/OBlvmiPSfmjxwBQtuxBBtytV", "info": {"w": 256, "h": 200, "size": 90269, "mimetype": "image/png", "thumbnail_url": "mxc://poa.st/OBlvmiPSfmjxwBQtuxBBtytV", "thumbnail_info": {"w": 256, "h": 200, "size": 90269, "mimetype": "image/png"}}, "msgtype": "m.sticker", "id": "tg-5136593470823072244", "net.maunium.telegram.sticker": {"pack": {"id": "5137713435085111297", "short_name": "OttiesStickers"}, "id": "5136593470823072244", "emoticons": ["🔦"]}}, {"body": "🏋️", "url": "mxc://poa.st/nBOfWYznPEQGfnqpcBpQMtAo", "info": {"w": 256, "h": 200, "size": 138396, "mimetype": "image/png", "thumbnail_url": "mxc://poa.st/nBOfWYznPEQGfnqpcBpQMtAo", "thumbnail_info": {"w": 256, "h": 200, "size": 138396, "mimetype": "image/png"}}, "msgtype": "m.sticker", "id": "tg-5136710083480125792", "net.maunium.telegram.sticker": {"pack": {"id": "5137713435085111297", "short_name": "OttiesStickers"}, "id": "5136710083480125792", "emoticons": ["🏋"]}}, {"body": "🛏", "url": "mxc://poa.st/HHiquTkpUqNUpWadajDcpogY", "info": {"w": 256, "h": 200, "size": 79854, "mimetype": "image/png", "thumbnail_url": "mxc://poa.st/HHiquTkpUqNUpWadajDcpogY", "thumbnail_info": {"w": 256, "h": 200, "size": 79854, "mimetype": "image/png"}}, "msgtype": "m.sticker", "id": "tg-5147851645257777591", "net.maunium.telegram.sticker": {"pack": {"id": "5137713435085111297", "short_name": "OttiesStickers"}, "id": "5147851645257777591", "emoticons": ["🛏"]}}, {"body": "😎", "url": "mxc://poa.st/TErXVDJFsrnPaphIatjcAFWK", "info": {"w": 256, "h": 200, "size": 116900, "mimetype": "image/png", "thumbnail_url": "mxc://poa.st/TErXVDJFsrnPaphIatjcAFWK", "thumbnail_info": {"w": 256, "h": 200, "size": 116900, "mimetype": "image/png"}}, "msgtype": "m.sticker", "id": "tg-5118522159701951112", "net.maunium.telegram.sticker": {"pack": {"id": "5137713435085111297", "short_name": "OttiesStickers"}, "id": "5118522159701951112", "emoticons": ["😎"]}}, {"body": "🙂", "url": "mxc://poa.st/TJqxuVBKlVnXKzIjTfhDygik", "info": {"w": 256, "h": 200, "size": 133701, "mimetype": "image/png", "thumbnail_url": "mxc://poa.st/TJqxuVBKlVnXKzIjTfhDygik", "thumbnail_info": {"w": 256, "h": 200, "size": 133701, "mimetype": "image/png"}}, "msgtype": "m.sticker", "id": "tg-5120839195773895199", "net.maunium.telegram.sticker": {"pack": {"id": "5137713435085111297", "short_name": "OttiesStickers"}, "id": "5120839195773895199", "emoticons": ["🙂"]}}, {"body": "🐴", "url": "mxc://poa.st/vctQQkGzxzeVNewEBJcIbHVv", "info": {"w": 256, "h": 256, "size": 98781, "mimetype": "image/png", "thumbnail_url": "mxc://poa.st/vctQQkGzxzeVNewEBJcIbHVv", "thumbnail_info": {"w": 256, "h": 256, "size": 98781, "mimetype": "image/png"}}, "msgtype": "m.sticker", "id": "tg-5129931598589854064", "net.maunium.telegram.sticker": {"pack": {"id": "5137713435085111297", "short_name": "OttiesStickers"}, "id": "5129931598589854064", "emoticons": ["🐴"]}}, {"body": "🐴", "url": "mxc://poa.st/HXtwnqowKwBzDZeUcjizgyGh", "info": {"w": 256, "h": 256, "size": 148295, "mimetype": "image/png", "thumbnail_url": "mxc://poa.st/HXtwnqowKwBzDZeUcjizgyGh", "thumbnail_info": {"w": 256, "h": 256, "size": 148295, "mimetype": "image/png"}}, "msgtype": "m.sticker", "id": "tg-5129692742573621819", "net.maunium.telegram.sticker": {"pack": {"id": "5137713435085111297", "short_name": "OttiesStickers"}, "id": "5129692742573621819", "emoticons": ["🐴"]}}, {"body": "🦝", "url": "mxc://poa.st/YFhtPVAkqnoVijOvfmwPwtJA", "info": {"w": 256, "h": 187, "size": 68188, "mimetype": "image/png", "thumbnail_url": "mxc://poa.st/YFhtPVAkqnoVijOvfmwPwtJA", "thumbnail_info": {"w": 256, "h": 187, "size": 68188, "mimetype": "image/png"}}, "msgtype": "m.sticker", "id": "tg-4956316380396782160", "net.maunium.telegram.sticker": {"pack": {"id": "5137713435085111297", "short_name": "OttiesStickers"}, "id": "4956316380396782160", "emoticons": ["🦝"]}}, {"body": "😳", "url": "mxc://poa.st/VAkVobPtleqkMHonqdZjkAFQ", "info": {"w": 256, "h": 187, "size": 78734, "mimetype": "image/png", "thumbnail_url": "mxc://poa.st/VAkVobPtleqkMHonqdZjkAFQ", "thumbnail_info": {"w": 256, "h": 187, "size": 78734, "mimetype": "image/png"}}, "msgtype": "m.sticker", "id": "tg-4983718550918136347", "net.maunium.telegram.sticker": {"pack": {"id": "5137713435085111297", "short_name": "OttiesStickers"}, "id": "4983718550918136347", "emoticons": ["😳"]}}, {"body": "😿", "url": "mxc://poa.st/qsPDeejzsZXOczsUwyNzBLMK", "info": {"w": 256, "h": 187, "size": 218473, "mimetype": "image/png", "thumbnail_url": "mxc://poa.st/qsPDeejzsZXOczsUwyNzBLMK", "thumbnail_info": {"w": 256, "h": 187, "size": 218473, "mimetype": "image/png"}}, "msgtype": "m.sticker", "id": "tg-5028381185684800436", "net.maunium.telegram.sticker": {"pack": {"id": "5137713435085111297", "short_name": "OttiesStickers"}, "id": "5028381185684800436", "emoticons": ["😿"]}}, {"body": "😳", "url": "mxc://poa.st/drvJjVQJNrvqmAFShuBFbjXc", "info": {"w": 256, "h": 200, "size": 117208, "mimetype": "image/png", "thumbnail_url": "mxc://poa.st/drvJjVQJNrvqmAFShuBFbjXc", "thumbnail_info": {"w": 256, "h": 200, "size": 117208, "mimetype": "image/png"}}, "msgtype": "m.sticker", "id": "tg-5136445247206720402", "net.maunium.telegram.sticker": {"pack": {"id": "5137713435085111297", "short_name": "OttiesStickers"}, "id": "5136445247206720402", "emoticons": ["😳"]}}, {"body": "🤬", "url": "mxc://poa.st/vQxsyYZwSQeIiZQsQYehpGTb", "info": {"w": 256, "h": 175, "size": 126860, "mimetype": "image/png", "thumbnail_url": "mxc://poa.st/vQxsyYZwSQeIiZQsQYehpGTb", "thumbnail_info": {"w": 256, "h": 175, "size": 126860, "mimetype": "image/png"}}, "msgtype": "m.sticker", "id": "tg-5166110126758691710", "net.maunium.telegram.sticker": {"pack": {"id": "5137713435085111297", "short_name": "OttiesStickers"}, "id": "5166110126758691710", "emoticons": ["🤬"]}}, {"body": "🤔", "url": "mxc://poa.st/iJViDFlfbNsTQgQjXDyZoFLA", "info": {"w": 256, "h": 150, "size": 90628, "mimetype": "image/png", "thumbnail_url": "mxc://poa.st/iJViDFlfbNsTQgQjXDyZoFLA", "thumbnail_info": {"w": 256, "h": 150, "size": 90628, "mimetype": "image/png"}}, "msgtype": "m.sticker", "id": "tg-5168198696340292080", "net.maunium.telegram.sticker": {"pack": {"id": "5137713435085111297", "short_name": "OttiesStickers"}, "id": "5168198696340292080", "emoticons": ["🤔"]}}, {"body": "❤️", "url": "mxc://poa.st/TNManIraMlxshwxgpgSvHwNU", "info": {"w": 256, "h": 150, "size": 118290, "mimetype": "image/png", "thumbnail_url": "mxc://poa.st/TNManIraMlxshwxgpgSvHwNU", "thumbnail_info": {"w": 256, "h": 150, "size": 118290, "mimetype": "image/png"}}, "msgtype": "m.sticker", "id": "tg-5174865099764007831", "net.maunium.telegram.sticker": {"pack": {"id": "5137713435085111297", "short_name": "OttiesStickers"}, "id": "5174865099764007831", "emoticons": ["❤"]}}, {"body": "❤️", "url": "mxc://poa.st/USMknVULvkcNddqZQsVhqPCg", "info": {"w": 256, "h": 150, "size": 106369, "mimetype": "image/png", "thumbnail_url": "mxc://poa.st/USMknVULvkcNddqZQsVhqPCg", "thumbnail_info": {"w": 256, "h": 150, "size": 106369, "mimetype": "image/png"}}, "msgtype": "m.sticker", "id": "tg-5183718118282756825", "net.maunium.telegram.sticker": {"pack": {"id": "5137713435085111297", "short_name": "OttiesStickers"}, "id": "5183718118282756825", "emoticons": ["❤"]}}, {"body": "🤗", "url": "mxc://poa.st/lFbBIsGEMfglQFAkJJJCnROp", "info": {"w": 256, "h": 150, "size": 116402, "mimetype": "image/png", "thumbnail_url": "mxc://poa.st/lFbBIsGEMfglQFAkJJJCnROp", "thumbnail_info": {"w": 256, "h": 150, "size": 116402, "mimetype": "image/png"}}, "msgtype": "m.sticker", "id": "tg-5183667042531672557", "net.maunium.telegram.sticker": {"pack": {"id": "5137713435085111297", "short_name": "OttiesStickers"}, "id": "5183667042531672557", "emoticons": ["🤗"]}}, {"body": "🤬", "url": "mxc://poa.st/iLEazBtBYbbWQYEWiKQFZHPl", "info": {"w": 256, "h": 150, "size": 116753, "mimetype": "image/png", "thumbnail_url": "mxc://poa.st/iLEazBtBYbbWQYEWiKQFZHPl", "thumbnail_info": {"w": 256, "h": 150, "size": 116753, "mimetype": "image/png"}}, "msgtype": "m.sticker", "id": "tg-5030909796140712664", "net.maunium.telegram.sticker": {"pack": {"id": "5137713435085111297", "short_name": "OttiesStickers"}, "id": "5030909796140712664", "emoticons": ["🤬"]}}]}